AUTHORS
LICENSE
MANIFEST.in
README.rst
setup.py
contrib/apache2/vhost_conf
contrib/mysql/create_django_session.sql
contrib/php/djangoSession.class.php
contrib/php/user.class.php
django_php_bridge/__init__.py
django_php_bridge.egg-info/PKG-INFO
django_php_bridge.egg-info/SOURCES.txt
django_php_bridge.egg-info/dependency_links.txt
django_php_bridge.egg-info/requires.txt
django_php_bridge.egg-info/top_level.txt
django_php_bridge/backends/__init__.py
django_php_bridge/backends/db.py