Metadata-Version: 1.1
Name: django-php-bridge
Version: 0.1.1
Summary: Authentication bridge between Django and PHP
Home-page: http://github.com/winhamwr/django-php-bridge/
Author: Wes Winham
Author-email: winhamwr@gmail.com
License: BSD
Platform: any
Classifier: Development Status :: 3 - Alpha
Classifier: Intended Audience :: Developers
Classifier: License :: OSI Approved :: BSD License
Classifier: Operating System :: OS Independent
Classifier: Programming Language :: Python
Classifier: Topic :: Software Development :: Libraries :: Python Modules
Classifier: Framework :: Django
